gama_client/__init__.py
gama_client/async_client.py
gama_client/command_types.py
gama_client/message_types.py
gama_client/sync_client.py
gama_client-1.2.4.dist-info/METADATA
gama_client-1.2.4.dist-info/WHEEL
gama_client-1.2.4.dist-info/licenses/LICENSE
gama_client-1.2.4.dist-info/RECORD
