Metadata-Version: 2.4
Name: gama_client
Version: 1.2.4
Summary: A python library to interact with Gama server
Project-URL: Homepage, https://github.com/gama-platform/Gama-client-python
Project-URL: Bug Tracker, https://github.com/gama-platform/Gama-client-python/issues
Author-email: Baptiste Lesquoy <baptistelesquoy@protonmail.com>
License: MIT License
License-File: LICENSE
Classifier: License :: OSI Approved :: MIT License
Classifier: Operating System :: OS Independent
Classifier: Programming Language :: Python :: 3
Requires-Python: >=3.10
Requires-Dist: nest-asyncio
Requires-Dist: websockets~=10.3
